INSTALL.txt
MANIFEST.in
README.txt
setup.cfg
setup.py
setup_egg.py
doc/Makefile
doc/source/conf.py
doc/source/contents.rst
doc/source/download.rst
doc/source/examples.rst
doc/source/install.rst
doc/source/tutorial.rst
doc/source/reference/agraph.rst
doc/source/reference/api_notes.rst
doc/source/reference/credits.rst
doc/source/reference/faq.rst
doc/source/reference/history.rst
doc/source/reference/index.rst
doc/source/reference/legal.rst
doc/source/reference/news.rst
doc/source/reference/related.rst
doc/source/static/empty.txt
doc/source/templates/index.html
doc/source/templates/indexsidebar.html
doc/source/templates/layout.html
doc/sphinxext/only_directives.py
examples/attributes.py
examples/django_simple.py
examples/miles.py
examples/miles_dat.txt.gz
examples/simple.py
examples/star.py
examples/subgraph.py
pygraphviz/__init__.py
pygraphviz/agraph.py
pygraphviz/graphviz.i
pygraphviz/graphviz.py
pygraphviz/graphviz_wrap.c
pygraphviz/release.py
pygraphviz.egg-info/PKG-INFO
pygraphviz.egg-info/SOURCES.txt
pygraphviz.egg-info/dependency_links.txt
pygraphviz.egg-info/top_level.txt
pygraphviz/tests/__init__.py
pygraphviz/tests/attributes.txt
pygraphviz/tests/graph.txt
pygraphviz/tests/layout_draw.txt
pygraphviz/tests/subgraph.txt
pygraphviz/tests/test.py