Metadata-Version: 1.0
Name: pygraphviz
Version: 0.99.1
Summary: Python interface to Graphviz
Home-page: http://networkx.lanl.gov/pygraphviz
Author: Aric Hagberg
Author-email: hagberg@lanl.gov
License: BSD
Download-URL: http://networkx.lanl.gov/wiki/download
Keywords: Networks,Graph Visualization,network,graph,graph drawing
Platform: Linux
Platform: Mac OSX
Platform: Windows XP/2000/NT
Classifier: Development Status :: 4 - Beta
Classifier: Intended Audience :: Developers
Classifier: Intended Audience :: Science/Research
Classifier: License :: OSI Approved :: BSD License
Classifier: Programming Language :: C
Classifier: Programming Language :: Python
Classifier: Topic :: Software Development :: Libraries :: Python Modules
Classifier: Topic :: Scientific/Engineering :: Information Analysis
Classifier: Topic :: Scientific/Engineering :: Mathematics
Classifier: Topic :: Scientific/Engineering :: Visualization
